rabifier/__init__.py
rabifier/config.json
rabifier/core.py
rabifier/rabmyfire.py
rabifier/utils.py
rabifier/data/non_rab_db.fasta
rabifier/data/rab_db.fasta
rabifier/data/rab_f.meme
rabifier/data/rab_subfamily.hmm
rabifier/data/rab_subfamily.hmm.h3f
rabifier/data/rab_subfamily.hmm.h3i
rabifier/data/rab_subfamily.hmm.h3m
rabifier/data/rab_subfamily.hmm.h3p
rabifier/data/rab_subfamily_model.json
rabifier-2.0.2.data/scripts/rabifier
rabifier-2.0.2.data/scripts/rabifier-mkdb
rabifier-2.0.2.dist-info/DESCRIPTION.rst
rabifier-2.0.2.dist-info/METADATA
rabifier-2.0.2.dist-info/RECORD
rabifier-2.0.2.dist-info/WHEEL
rabifier-2.0.2.dist-info/metadata.json
rabifier-2.0.2.dist-info/top_level.txt
