Metadata-Version: 2.0
Name: rabifier
Version: 2.0.2
Summary: A bioinformatic classifier of Rab GTPases
Home-page: https://github.com/evocell/rabifier
Author: Jaroslaw Surkont
Author-email: jarek.surkont@gmail.com
License: GPLv3
Keywords: Rab,classifier,bioinformatics
Platform: UNKNOWN
Classifier: Development Status :: 5 - Production/Stable
Classifier: Intended Audience :: Science/Research
Classifier: Topic :: Scientific/Engineering :: Bio-Informatics
Classifier: License :: OSI Approved :: GNU General Public License v3 (GPLv3)
Classifier: Natural Language :: English
Classifier: Programming Language :: Python :: 2.7
Classifier: Programming Language :: Python :: 3.4
Requires-Dist: biopython
Requires-Dist: numpy
Requires-Dist: scipy
Provides-Extra: plotting
Requires-Dist: matplotlib; extra == 'plotting'
